Mynewpack/__init__.py
Mynewpack/add.py
Mynewpack/sub.py
G_NAGARJUNA_REDDY-0.0.1.dist-info/LICENSE.txt
G_NAGARJUNA_REDDY-0.0.1.dist-info/METADATA
G_NAGARJUNA_REDDY-0.0.1.dist-info/WHEEL
G_NAGARJUNA_REDDY-0.0.1.dist-info/top_level.txt
G_NAGARJUNA_REDDY-0.0.1.dist-info/RECORD
