Metadata-Version: 2.1
Name: G-NAGARJUNA-REDDY
Version: 0.0.1
Summary: NAGARJUNA
Home-page: UNKNOWN
Author: Nagarjuna
Author-email: nagarjunagolamari@gmail.com
License: UNKNOWN
Keywords: add,sub,mathematics,python tutorial,Nagarjuna
Platform: UNKNOWN
Classifier: Programming Language :: Python :: 3
Classifier: License :: OSI Approved :: MIT License
Classifier: Operating System :: OS Independent
